{
  "CF105086215": {
    "contest_id": 894,
    "language": "GNU C++17",
    "path": "codeforces/894/A.cpp",
    "platform": "Codeforces",
    "problem_index": "A",
    "problem_name": "QAQ",
    "problem_url": "https://codeforces.com/contest/894/problem/A",
    "submission_id": "CF105086215",
    "submission_url": "https://codeforces.com/contest/894/submission/105086215",
    "tags": [
      "brute force",
      "dp",
      "*800"
    ],
    "timestamp": "Jan/22/2021 20:25"
  },
  "CF105090092": {
    "contest_id": 1369,
    "language": "GNU C++17",
    "path": "codeforces/1369/A.cpp",
    "platform": "Codeforces",
    "problem_index": "A",
    "problem_name": "FashionabLee",
    "problem_url": "https://codeforces.com/contest/1369/problem/A",
    "submission_id": "CF105090092",
    "submission_url": "https://codeforces.com/contest/1369/submission/105090092",
    "tags": [
      "geometry",
      "math",
      "*800"
    ],
    "timestamp": "Jan/22/2021 21:08"
  },
  "CF105098752": {
    "contest_id": 1472,
    "language": "GNU C++17",
    "path": "codeforces/1472/D.cpp",
    "platform": "Codeforces",
    "problem_index": "D",
    "problem_name": "Even-Odd Game",
    "problem_url": "https://codeforces.com/contest/1472/problem/D",
    "submission_id": "CF105098752",
    "submission_url": "https://codeforces.com/contest/1472/submission/105098752",
    "tags": [
      "dp",
      "games",
      "greedy",
      "sortings",
      "*1200"
    ],
    "timestamp": "Jan/22/2021 22:45"
  },
  "CF105143471": {
    "contest_id": 1265,
    "language": "GNU C++17",
    "path": "codeforces/1265/C.cpp",
    "platform": "Codeforces",
    "problem_index": "C",
    "problem_name": "Beautiful Regional Contest",
    "problem_url": "https://codeforces.com/contest/1265/problem/C",
    "submission_id": "CF105143471",
    "submission_url": "https://codeforces.com/contest/1265/submission/105143471",
    "tags": [
      "greedy",
      "implementation",
      "*1500"
    ],
    "timestamp": "Jan/23/2021 13:54"
  },
  "CF105145628": {
    "contest_id": 1178,
    "language": "GNU C++17",
    "path": "codeforces/1178/B.cpp",
    "platform": "Codeforces",
    "problem_index": "B",
    "problem_name": "WOW Factor",
    "problem_url": "https://codeforces.com/contest/1178/problem/B",
    "submission_id": "CF105145628",
    "submission_url": "https://codeforces.com/contest/1178/submission/105145628",
    "tags": [
      "dp",
      "strings",
      "*1300"
    ],
    "timestamp": "Jan/23/2021 14:25"
  },
  "CF105180058": {
    "contest_id": 115,
    "language": "GNU C++17",
    "path": "codeforces/115/A.cpp",
    "platform": "Codeforces",
    "problem_index": "A",
    "problem_name": "Party",
    "problem_url": "https://codeforces.com/contest/115/problem/A",
    "submission_id": "CF105180058",
    "submission_url": "https://codeforces.com/contest/115/submission/105180058",
    "tags": [
      "dfs and similar",
      "graphs",
      "trees",
      "*900"
    ],
    "timestamp": "Jan/23/2021 23:02"
  },
  "CF105219382": {
    "contest_id": 948,
    "language": "GNU C++17",
    "path": "codeforces/948/A.cpp",
    "platform": "Codeforces",
    "problem_index": "A",
    "problem_name": "Protect Sheep",
    "problem_url": "https://codeforces.com/contest/948/problem/A",
    "submission_id": "CF105219382",
    "submission_url": "https://codeforces.com/contest/948/submission/105219382",
    "tags": [
      "brute force",
      "dfs and similar",
      "graphs",
      "implementation",
      "*900"
    ],
    "timestamp": "Jan/24/2021 14:31"
  },
  "CF105220829": {
    "contest_id": 1057,
    "language": "GNU C++17",
    "path": "codeforces/1057/A.cpp",
    "platform": "Codeforces",
    "problem_index": "A",
    "problem_name": "Bmail Computer Network",
    "problem_url": "https://codeforces.com/contest/1057/problem/A",
    "submission_id": "CF105220829",
    "submission_url": "https://codeforces.com/contest/1057/submission/105220829",
    "tags": [
      "*special problem",
      "dfs and similar",
      "trees",
      "*900"
    ],
    "timestamp": "Jan/24/2021 14:51"
  },
  "CF105221518": {
    "contest_id": 500,
    "language": "GNU C++17",
    "path": "codeforces/500/A.cpp",
    "platform": "Codeforces",
    "problem_index": "A",
    "problem_name": "New Year Transportation",
    "problem_url": "https://codeforces.com/contest/500/problem/A",
    "submission_id": "CF105221518",
    "submission_url": "https://codeforces.com/contest/500/submission/105221518",
    "tags": [
      "dfs and similar",
      "graphs",
      "implementation",
      "*1000"
    ],
    "timestamp": "Jan/24/2021 15:01"
  },
  "CF105222860": {
    "contest_id": 1020,
    "language": "GNU C++17",
    "path": "codeforces/1020/B.cpp",
    "platform": "Codeforces",
    "problem_index": "B",
    "problem_name": "Badge",
    "problem_url": "https://codeforces.com/contest/1020/problem/B",
    "submission_id": "CF105222860",
    "submission_url": "https://codeforces.com/contest/1020/submission/105222860",
    "tags": [
      "brute force",
      "dfs and similar",
      "graphs",
      "*1000"
    ],
    "timestamp": "Jan/24/2021 15:19"
  },
  "CF105225496": {
    "contest_id": 1033,
    "language": "GNU C++17",
    "path": "codeforces/1033/A.cpp",
    "platform": "Codeforces",
    "problem_index": "A",
    "problem_name": "King Escape",
    "problem_url": "https://codeforces.com/contest/1033/problem/A",
    "submission_id": "CF105225496",
    "submission_url": "https://codeforces.com/contest/1033/submission/105225496",
    "tags": [
      "dfs and similar",
      "graphs",
      "implementation",
      "*1000"
    ],
    "timestamp": "Jan/24/2021 15:56"
  },
  "CF105226362": {
    "contest_id": 727,
    "language": "GNU C++17",
    "path": "codeforces/727/A.cpp",
    "platform": "Codeforces",
    "problem_index": "A",
    "problem_name": "Transformation: from A to B",
    "problem_url": "https://codeforces.com/contest/727/problem/A",
    "submission_id": "CF105226362",
    "submission_url": "https://codeforces.com/contest/727/submission/105226362",
    "tags": [
      "brute force",
      "dfs and similar",
      "math",
      "*1000"
    ],
    "timestamp": "Jan/24/2021 16:08"
  },
  "CF105227092": {
    "contest_id": 1472,
    "language": "GNU C++17",
    "path": "codeforces/1472/C.cpp",
    "platform": "Codeforces",
    "problem_index": "C",
    "problem_name": "Long Jumps",
    "problem_url": "https://codeforces.com/contest/1472/problem/C",
    "submission_id": "CF105227092",
    "submission_url": "https://codeforces.com/contest/1472/submission/105227092",
    "tags": [
      "dp",
      "graphs",
      "*1100"
    ],
    "timestamp": "Jan/24/2021 16:18"
  },
  "CF105244249": {
    "contest_id": 1455,
    "language": "GNU C++17",
    "path": "codeforces/1455/C.cpp",
    "platform": "Codeforces",
    "problem_index": "C",
    "problem_name": "Ping-pong",
    "problem_url": "https://codeforces.com/contest/1455/problem/C",
    "submission_id": "CF105244249",
    "submission_url": "https://codeforces.com/contest/1455/submission/105244249",
    "tags": [
      "constructive algorithms",
      "games",
      "math",
      "*1100"
    ],
    "timestamp": "Jan/24/2021 20:23"
  },
  "CF105246418": {
    "contest_id": 1408,
    "language": "GNU C++17",
    "path": "codeforces/1408/A.cpp",
    "platform": "Codeforces",
    "problem_index": "A",
    "problem_name": "Circle Coloring",
    "problem_url": "https://codeforces.com/contest/1408/problem/A",
    "submission_id": "CF105246418",
    "submission_url": "https://codeforces.com/contest/1408/submission/105246418",
    "tags": [
      "constructive algorithms",
      "*800"
    ],
    "timestamp": "Jan/24/2021 21:08"
  },
  "CF105250900": {
    "contest_id": 47,
    "language": "GNU C++17 (64)",
    "path": "codeforces/47/A.cpp",
    "platform": "Codeforces",
    "problem_index": "A",
    "problem_name": "Triangular numbers",
    "problem_url": "https://codeforces.com/contest/47/problem/A",
    "submission_id": "CF105250900",
    "submission_url": "https://codeforces.com/contest/47/submission/105250900",
    "tags": [
      "brute force",
      "math",
      "*800"
    ],
    "timestamp": "Jan/24/2021 22:48"
  },
  "CF105251229": {
    "contest_id": 110,
    "language": "GNU C++17 (64)",
    "path": "codeforces/110/A.cpp",
    "platform": "Codeforces",
    "problem_index": "A",
    "problem_name": "Nearly Lucky Number",
    "problem_url": "https://codeforces.com/contest/110/problem/A",
    "submission_id": "CF105251229",
    "submission_url": "https://codeforces.com/contest/110/submission/105251229",
    "tags": [
      "implementation",
      "*800"
    ],
    "timestamp": "Jan/24/2021 22:55"
  },
  "CF105318768": {
    "contest_id": 1475,
    "language": "GNU C++17 (64)",
    "path": "codeforces/1475/A.cpp",
    "platform": "Codeforces",
    "problem_index": "A",
    "problem_name": "Odd Divisor",
    "problem_url": "https://codeforces.com/contest/1475/problem/A",
    "submission_id": "CF105318768",
    "submission_url": "https://codeforces.com/contest/1475/submission/105318768",
    "tags": [
      "math",
      "number theory",
      "*900"
    ],
    "timestamp": "Jan/25/2021 18:07"
  },
  "CF105337522": {
    "contest_id": 1475,
    "language": "GNU C++17 (64)",
    "path": "codeforces/1475/B.cpp",
    "platform": "Codeforces",
    "problem_index": "B",
    "problem_name": "New Year's Number",
    "problem_url": "https://codeforces.com/contest/1475/problem/B",
    "submission_id": "CF105337522",
    "submission_url": "https://codeforces.com/contest/1475/submission/105337522",
    "tags": [
      "brute force",
      "dp",
      "math",
      "*900"
    ],
    "timestamp": "Jan/25/2021 18:17"
  },
  "CF105409826": {
    "contest_id": 1475,
    "language": "GNU C++17 (64)",
    "path": "codeforces/1475/C.cpp",
    "platform": "Codeforces",
    "problem_index": "C",
    "problem_name": "Ball in Berland",
    "problem_url": "https://codeforces.com/contest/1475/problem/C",
    "submission_id": "CF105409826",
    "submission_url": "https://codeforces.com/contest/1475/submission/105409826",
    "tags": [
      "combinatorics",
      "graphs",
      "math",
      "*1400"
    ],
    "timestamp": "Jan/25/2021 21:16"
  },
  "CF105506361": {
    "contest_id": 1421,
    "language": "GNU C++17 (64)",
    "path": "codeforces/1421/A.cpp",
    "platform": "Codeforces",
    "problem_index": "A",
    "problem_name": "XORwice",
    "problem_url": "https://codeforces.com/contest/1421/problem/A",
    "submission_id": "CF105506361",
    "submission_url": "https://codeforces.com/contest/1421/submission/105506361",
    "tags": [
      "bitmasks",
      "greedy",
      "math",
      "*800"
    ],
    "timestamp": "Jan/26/2021 20:52"
  },
  "CF105510508": {
    "contest_id": 1373,
    "language": "GNU C++17 (64)",
    "path": "codeforces/1373/B.cpp",
    "platform": "Codeforces",
    "problem_index": "B",
    "problem_name": "01 Game",
    "problem_url": "https://codeforces.com/contest/1373/problem/B",
    "submission_id": "CF105510508",
    "submission_url": "https://codeforces.com/contest/1373/submission/105510508",
    "tags": [
      "games",
      "*900"
    ],
    "timestamp": "Jan/26/2021 21:55"
  },
  "CF105580788": {
    "contest_id": 1051,
    "language": "GNU C++17 (64)",
    "path": "codeforces/1051/B.cpp",
    "platform": "Codeforces",
    "problem_index": "B",
    "problem_name": "Relatively Prime Pairs",
    "problem_url": "https://codeforces.com/contest/1051/problem/B",
    "submission_id": "CF105580788",
    "submission_url": "https://codeforces.com/contest/1051/submission/105580788",
    "tags": [
      "greedy",
      "math",
      "number theory",
      "*1000"
    ],
    "timestamp": "Jan/27/2021 17:18"
  },
  "CF105681570": {
    "contest_id": 1478,
    "language": "GNU C++17 (64)",
    "path": "codeforces/1478/A.cpp",
    "platform": "Codeforces",
    "problem_index": "A",
    "problem_name": "Nezzar and Colorful Balls",
    "problem_url": "https://codeforces.com/contest/1478/problem/A",
    "submission_id": "CF105681570",
    "submission_url": "https://codeforces.com/contest/1478/submission/105681570",
    "tags": [
      "brute force",
      "greedy",
      "*800"
    ],
    "timestamp": "Jan/28/2021 17:40"
  },
  "CF105777410": {
    "contest_id": 119,
    "language": "GNU C++17 (64)",
    "path": "codeforces/119/A.cpp",
    "platform": "Codeforces",
    "problem_index": "A",
    "problem_name": "Epic Game",
    "problem_url": "https://codeforces.com/contest/119/problem/A",
    "submission_id": "CF105777410",
    "submission_url": "https://codeforces.com/contest/119/submission/105777410",
    "tags": [
      "implementation",
      "*800"
    ],
    "timestamp": "Jan/28/2021 21:22"
  },
  "CF105777989": {
    "contest_id": 915,
    "language": "GNU C++17 (64)",
    "path": "codeforces/915/A.cpp",
    "platform": "Codeforces",
    "problem_index": "A",
    "problem_name": "Garden",
    "problem_url": "https://codeforces.com/contest/915/problem/A",
    "submission_id": "CF105777989",
    "submission_url": "https://codeforces.com/contest/915/submission/105777989",
    "tags": [
      "implementation",
      "*900"
    ],
    "timestamp": "Jan/28/2021 21:29"
  },
  "CF105781543": {
    "contest_id": 56,
    "language": "GNU C++17 (64)",
    "path": "codeforces/56/B.cpp",
    "platform": "Codeforces",
    "problem_index": "B",
    "problem_name": "Spoilt Permutation",
    "problem_url": "https://codeforces.com/contest/56/problem/B",
    "submission_id": "CF105781543",
    "submission_url": "https://codeforces.com/contest/56/submission/105781543",
    "tags": [
      "implementation",
      "*1300"
    ],
    "timestamp": "Jan/28/2021 22:17"
  },
  "CF105782099": {
    "contest_id": 56,
    "language": "GNU C++17 (64)",
    "path": "codeforces/56/A.cpp",
    "platform": "Codeforces",
    "problem_index": "A",
    "problem_name": "Bar",
    "problem_url": "https://codeforces.com/contest/56/problem/A",
    "submission_id": "CF105782099",
    "submission_url": "https://codeforces.com/contest/56/submission/105782099",
    "tags": [
      "implementation",
      "*1000"
    ],
    "timestamp": "Jan/28/2021 22:25"
  },
  "CF105844269": {
    "contest_id": 263,
    "language": "GNU C++17 (64)",
    "path": "codeforces/263/A.cpp",
    "platform": "Codeforces",
    "problem_index": "A",
    "problem_name": "Beautiful Matrix",
    "problem_url": "https://codeforces.com/contest/263/problem/A",
    "submission_id": "CF105844269",
    "submission_url": "https://codeforces.com/contest/263/submission/105844269",
    "tags": [
      "implementation",
      "*800"
    ],
    "timestamp": "Jan/29/2021 16:27"
  },
  "CF105873114": {
    "contest_id": 1476,
    "language": "GNU C++17 (64)",
    "path": "codeforces/1476/A.cpp",
    "platform": "Codeforces",
    "problem_index": "A",
    "problem_name": "K-divisible Sum",
    "problem_url": "https://codeforces.com/contest/1476/problem/A",
    "submission_id": "CF105873114",
    "submission_url": "https://codeforces.com/contest/1476/submission/105873114",
    "tags": [
      "binary search",
      "constructive algorithms",
      "greedy",
      "math",
      "*1000"
    ],
    "timestamp": "Jan/29/2021 17:56"
  },
  "CF105936964": {
    "contest_id": 1476,
    "language": "GNU C++17 (64)",
    "path": "codeforces/1476/B.cpp",
    "platform": "Codeforces",
    "problem_index": "B",
    "problem_name": "Inflation",
    "problem_url": "https://codeforces.com/contest/1476/problem/B",
    "submission_id": "CF105936964",
    "submission_url": "https://codeforces.com/contest/1476/submission/105936964",
    "tags": [
      "binary search",
      "brute force",
      "greedy",
      "math",
      "*1300"
    ],
    "timestamp": "Jan/29/2021 19:32"
  },
  "CF105987698": {
    "contest_id": 1401,
    "language": "GNU C++17 (64)",
    "path": "codeforces/1401/A.cpp",
    "platform": "Codeforces",
    "problem_index": "A",
    "problem_name": "Distance and Axis",
    "problem_url": "https://codeforces.com/contest/1401/problem/A",
    "submission_id": "CF105987698",
    "submission_url": "https://codeforces.com/contest/1401/submission/105987698",
    "tags": [
      "constructive algorithms",
      "math",
      "*900"
    ],
    "timestamp": "Jan/30/2021 09:55"
  },
  "CF105990258": {
    "contest_id": 1401,
    "language": "GNU C++17 (64)",
    "path": "codeforces/1401/B.cpp",
    "platform": "Codeforces",
    "problem_index": "B",
    "problem_name": "Ternary Sequence",
    "problem_url": "https://codeforces.com/contest/1401/problem/B",
    "submission_id": "CF105990258",
    "submission_url": "https://codeforces.com/contest/1401/submission/105990258",
    "tags": [
      "constructive algorithms",
      "greedy",
      "math",
      "*1100"
    ],
    "timestamp": "Jan/30/2021 10:23"
  },
  "CF105993795": {
    "contest_id": 467,
    "language": "GNU C++17 (64)",
    "path": "codeforces/467/B.cpp",
    "platform": "Codeforces",
    "problem_index": "B",
    "problem_name": "Fedor and New Game",
    "problem_url": "https://codeforces.com/contest/467/problem/B",
    "submission_id": "CF105993795",
    "submission_url": "https://codeforces.com/contest/467/submission/105993795",
    "tags": [
      "bitmasks",
      "brute force",
      "constructive algorithms",
      "implementation",
      "*1100"
    ],
    "timestamp": "Jan/30/2021 11:02"
  },
  "CF106001049": {
    "contest_id": 1,
    "language": "GNU C++17 (64)",
    "path": "codeforces/1/A.cpp",
    "platform": "Codeforces",
    "problem_index": "A",
    "problem_name": "Theatre Square",
    "problem_url": "https://codeforces.com/contest/1/problem/A",
    "submission_id": "CF106001049",
    "submission_url": "https://codeforces.com/contest/1/submission/106001049",
    "tags": [
      "math",
      "*1000"
    ],
    "timestamp": "Jan/30/2021 12:21"
  },
  "CF106015636": {
    "contest_id": 755,
    "language": "GNU C++17 (64)",
    "path": "codeforces/755/C.cpp",
    "platform": "Codeforces",
    "problem_index": "C",
    "problem_name": "PolandBall and Forest",
    "problem_url": "https://codeforces.com/contest/755/problem/C",
    "submission_id": "CF106015636",
    "submission_url": "https://codeforces.com/contest/755/submission/106015636",
    "tags": [
      "dfs and similar",
      "dsu",
      "graphs",
      "interactive",
      "trees",
      "*1300"
    ],
    "timestamp": "Jan/30/2021 14:44"
  },
  "CF106051834": {
    "contest_id": 60,
    "language": "GNU C++17 (64)",
    "path": "codeforces/60/A.cpp",
    "platform": "Codeforces",
    "problem_index": "A",
    "problem_name": "Where Are My Flakes?",
    "problem_url": "https://codeforces.com/contest/60/problem/A",
    "submission_id": "CF106051834",
    "submission_url": "https://codeforces.com/contest/60/submission/106051834",
    "tags": [
      "implementation",
      "two pointers",
      "*1300"
    ],
    "timestamp": "Jan/30/2021 22:27"
  },
  "CF106133954": {
    "contest_id": 381,
    "language": "GNU C++17 (64)",
    "path": "codeforces/381/A.cpp",
    "platform": "Codeforces",
    "problem_index": "A",
    "problem_name": "Sereja and Dima",
    "problem_url": "https://codeforces.com/contest/381/problem/A",
    "submission_id": "CF106133954",
    "submission_url": "https://codeforces.com/contest/381/submission/106133954",
    "tags": [
      "greedy",
      "implementation",
      "two pointers",
      "*800"
    ],
    "timestamp": "Jan/31/2021 22:01"
  },
  "CF106135458": {
    "contest_id": 339,
    "language": "GNU C++17 (64)",
    "path": "codeforces/339/A.cpp",
    "platform": "Codeforces",
    "problem_index": "A",
    "problem_name": "Helpful Maths",
    "problem_url": "https://codeforces.com/contest/339/problem/A",
    "submission_id": "CF106135458",
    "submission_url": "https://codeforces.com/contest/339/submission/106135458",
    "tags": [
      "greedy",
      "implementation",
      "sortings",
      "strings",
      "*800"
    ],
    "timestamp": "Jan/31/2021 22:25"
  },
  "CF106206303": {
    "contest_id": 679,
    "language": "GNU C++17 (64)",
    "path": "codeforces/679/A.cpp",
    "platform": "Codeforces",
    "problem_index": "A",
    "problem_name": "Bear and Prime 100",
    "problem_url": "https://codeforces.com/contest/679/problem/A",
    "submission_id": "CF106206303",
    "submission_url": "https://codeforces.com/contest/679/submission/106206303",
    "tags": [
      "constructive algorithms",
      "interactive",
      "math",
      "*1400"
    ],
    "timestamp": "Feb/01/2021 18:37"
  }
}